[
  {
    "id": "1",
    "title": "Yazlık Mezar Bakım Kampanyası",
    "description": "Yaz aylarında mezarlarınızın bakımı için özel indirimli paketlerimizden faydalanın!",
    "images": [
      "https://images.unsplash.com/photo-1578662996442-48f60103fc96?w=400&h=300&fit=crop",
      "https://images.unsplash.com/photo-1571019613454-1cb2f99b2d8b?w=400&h=300&fit=crop"
    ],
    "tag": "Kampanya",
    "date": "Haziran 2024",
    "isActive": true
  },
  {
    "id": "2",
    "title": "Mermer Mezar Taşları %25 İndirim",
    "description": "Kaliteli mermer mezar taşlarında özel indirim fırsatı! Sınırlı süreyle geçerli.",
    "images": [
      "https://images.unsplash.com/photo-1578662996442-48f60103fc96?w=400&h=300&fit=crop"
    ],
    "tag": "Kampanya",
    "date": "Mayıs 2024",
    "isActive": true
  }
]
